noidy/__init__.py
noidy/__main__.py
noidy/n2tminter.py
noidy-0.2.0.dist-info/entry_points.txt
noidy-0.2.0.dist-info/LICENSE
noidy-0.2.0.dist-info/WHEEL
noidy-0.2.0.dist-info/METADATA
noidy-0.2.0.dist-info/RECORD
