Metadata-Version: 2.1
Name: noidy
Version: 0.2.0
Summary: NOID generator in python with JSON persistence.
License: MIT
Author: datadavev
Author-email: 605409+datadavev@users.noreply.github.com
Requires-Python: >=3.9,<4.0
Classifier: License :: OSI Approved :: MIT License
Classifier: Programming Language :: Python :: 3
Classifier: Programming Language :: Python :: 3.10
Classifier: Programming Language :: Python :: 3.9
Requires-Dist: click (>=8.0.3,<9.0.0)
